spekpy/DataTables.py
spekpy/IO.py
spekpy/SpekAniso.py
spekpy/SpekConstants.py
spekpy/SpekHelpers.py
spekpy/SpekModel.py
spekpy/SpekPy.py
spekpy/SpekState.py
spekpy/SpekTools.py
spekpy/__init__.py
"spekpy/data/matl_def/1,2-Dichlorobenzene.comp"
"spekpy/data/matl_def/1,2-Dichloroethane.comp"
"spekpy/data/matl_def/1,3-Butadiene (Liquid).comp"
"spekpy/data/matl_def/1,3-Butadiene.comp"
spekpy/data/matl_def/1-Butene (Liquid).comp
spekpy/data/matl_def/1-Butene.comp
spekpy/data/matl_def/A-150 Tissue-Equivalent Gas.comp
spekpy/data/matl_def/A-150 Tissue-Equivalent Plastic.comp
spekpy/data/matl_def/Ac.comp
spekpy/data/matl_def/Acetone.comp
spekpy/data/matl_def/Acetylene.comp
spekpy/data/matl_def/Adenine.comp
spekpy/data/matl_def/Adipose Tissue (ICRP).comp
spekpy/data/matl_def/Adipose Tissue (ICRU).comp
"spekpy/data/matl_def/Adipose Tissue Substitute (AP-L2, Aqueous).comp"
"spekpy/data/matl_def/Adipose Tissue Substitute (AP-SF1, Epoxy-based).comp"
"spekpy/data/matl_def/Adipose Tissue Substitute (AP6, Epoxy-based).comp"
spekpy/data/matl_def/Ag.comp
spekpy/data/matl_def/Air Dry (Near Sea Level).comp
spekpy/data/matl_def/Air-Equivalent Plastic (C-552).comp
spekpy/data/matl_def/Air.comp
spekpy/data/matl_def/Al.comp
spekpy/data/matl_def/Alanine.comp
spekpy/data/matl_def/Aluminum Alloy (Type 1100).comp
spekpy/data/matl_def/Aluminum Alloy (Type 2014).comp
spekpy/data/matl_def/Aluminum Alloy (Type 6061).comp
spekpy/data/matl_def/Aluminum Oxide.comp
spekpy/data/matl_def/Amber.comp
spekpy/data/matl_def/Ammonia.comp
spekpy/data/matl_def/Ammonium Formate.comp
spekpy/data/matl_def/Aniline.comp
spekpy/data/matl_def/Anthracene.comp
spekpy/data/matl_def/Ar.comp
spekpy/data/matl_def/As.comp
spekpy/data/matl_def/At.comp
spekpy/data/matl_def/Au.comp
spekpy/data/matl_def/B.comp
spekpy/data/matl_def/Ba.comp
spekpy/data/matl_def/Bakelite.comp
spekpy/data/matl_def/Barium Fluoride.comp
spekpy/data/matl_def/Barium Sulfate.comp
spekpy/data/matl_def/Be.comp
spekpy/data/matl_def/Benzene.comp
spekpy-2.5.3.dist-info/METADATA
spekpy-2.5.3.dist-info/WHEEL
spekpy-2.5.3.dist-info/RECORD
