Metadata-Version: 2.4
Name: spekpy
Version: 2.5.3
Summary: A Python software toolkit for modelling the x-ray spectra from x-ray tubes
Project-URL: Repository, https://bitbucket.org/spekpy/spekpy_release
Project-URL: Documentation, https://bitbucket.org/spekpy/spekpy_release/wiki/Home
Project-URL: Issues, https://bitbucket.org/spekpy/spekpy_release/issues?status=new&status=open
Author-email: Gavin Poludniowski <gpoludniowski@gmail.com>
License: MIT License
Keywords: photon energy distribution,radiation physics,spectral simulation,x-ray spectra,x-ray tube modeling
Classifier: Development Status :: 5 - Production/Stable
Classifier: Intended Audience :: Science/Research
Classifier: Programming Language :: Python
Classifier: Programming Language :: Python :: 2
Classifier: Programming Language :: Python :: 2.6
Classifier: Programming Language :: Python :: 3
Classifier: Programming Language :: Python :: 3.6
Classifier: Topic :: Scientific/Engineering :: Physics
Requires-Python: >=3.6
Requires-Dist: matplotlib
Requires-Dist: scipy
